LICENSE
MANIFEST.in
README.rst
setup.cfg
setup.py
django4_js_urls.egg-info/PKG-INFO
django4_js_urls.egg-info/SOURCES.txt
django4_js_urls.egg-info/dependency_links.txt
django4_js_urls.egg-info/not-zip-safe
django4_js_urls.egg-info/requires.txt
django4_js_urls.egg-info/top_level.txt
js_urls/__init__.py
js_urls/apps.py
js_urls/serializer.py
js_urls/views.py
js_urls/conf/__init__.py
js_urls/conf/settings.py
js_urls/templates/js_urls/js_urls.js
js_urls/utils/__init__.py
js_urls/utils/compat.py
js_urls/utils/text.py